ape_filecoin/__init__.py
ape_filecoin/ecosystem.py
ape_filecoin/py.typed
ape_filecoin/version.py
ape_filecoin-0.1.1.dist-info/LICENSE
ape_filecoin-0.1.1.dist-info/METADATA
ape_filecoin-0.1.1.dist-info/WHEEL
ape_filecoin-0.1.1.dist-info/top_level.txt
ape_filecoin-0.1.1.dist-info/RECORD
