Metadata-Version: 2.1
Name: ape-filecoin
Version: 0.1.1
Summary: ape-filecoin: Ape Ecosystem Plugin for Filecoin
Home-page: https://github.com/z80dev/ape-filecoin
Author: z80
Author-email: z80@ophy.xyz
License: Apache-2.0
Keywords: ethereum
Classifier: Development Status :: 5 - Production/Stable
Classifier: Intended Audience :: Developers
Classifier: License :: OSI Approved :: Apache Software License
Classifier: Natural Language :: English
Classifier: Operating System :: MacOS
Classifier: Operating System :: POSIX
Classifier: Programming Language :: Python :: 3
Classifier: Programming Language :: Python :: 3.8
Classifier: Programming Language :: Python :: 3.9
Classifier: Programming Language :: Python :: 3.10
Requires-Python: >=3.8,<4
License-File: LICENSE
Provides-Extra: dev
Requires-Dist: pytest (>=6.0) ; extra == 'dev'
Requires-Dist: pytest-xdist ; extra == 'dev'
Requires-Dist: pytest-cov ; extra == 'dev'
Requires-Dist: hypothesis (<7.0,>=6.2.0) ; extra == 'dev'
Requires-Dist: black (>=22.12.0) ; extra == 'dev'
Requires-Dist: mypy (>=0.991) ; extra == 'dev'
Requires-Dist: types-setuptools ; extra == 'dev'
Requires-Dist: flake8 (>=5.0.4) ; extra == 'dev'
Requires-Dist: isort (>=5.10.1) ; extra == 'dev'
Requires-Dist: mdformat (>=0.7.16) ; extra == 'dev'
Requires-Dist: mdformat-gfm (>=0.3.5) ; extra == 'dev'
Requires-Dist: mdformat-frontmatter (>=0.4.1) ; extra == 'dev'
Requires-Dist: setuptools ; extra == 'dev'
Requires-Dist: wheel ; extra == 'dev'
Requires-Dist: twine ; extra == 'dev'
Requires-Dist: commitizen ; extra == 'dev'
Requires-Dist: pre-commit ; extra == 'dev'
Requires-Dist: pytest-watch ; extra == 'dev'
Requires-Dist: IPython ; extra == 'dev'
Requires-Dist: ipdb ; extra == 'dev'
Provides-Extra: lint
Requires-Dist: black (>=22.12.0) ; extra == 'lint'
Requires-Dist: mypy (>=0.991) ; extra == 'lint'
Requires-Dist: types-setuptools ; extra == 'lint'
Requires-Dist: flake8 (>=5.0.4) ; extra == 'lint'
Requires-Dist: isort (>=5.10.1) ; extra == 'lint'
Requires-Dist: mdformat (>=0.7.16) ; extra == 'lint'
Requires-Dist: mdformat-gfm (>=0.3.5) ; extra == 'lint'
Requires-Dist: mdformat-frontmatter (>=0.4.1) ; extra == 'lint'
Provides-Extra: release
Requires-Dist: setuptools ; extra == 'release'
Requires-Dist: wheel ; extra == 'release'
Requires-Dist: twine ; extra == 'release'
Provides-Extra: test
Requires-Dist: pytest (>=6.0) ; extra == 'test'
Requires-Dist: pytest-xdist ; extra == 'test'
Requires-Dist: pytest-cov ; extra == 'test'
Requires-Dist: hypothesis (<7.0,>=6.2.0) ; extra == 'test'
